{
    "org.apache.cordova.vibration": {
        "source": {
            "type": "registry",
            "id": "org.apache.cordova.vibration"
        }
    },
    "de.appplant.cordova.plugin.local-notification": {
        "source": {
            "type": "git",
            "url": "https://github.com/katzer/cordova-plugin-local-notifications.git",
            "subdir": "."
        }
    },
    "org.apache.cordova.device": {
        "source": {
            "type": "registry",
            "id": "org.apache.cordova.device"
        }
    },
    "android.support.v4": {
        "source": {
            "type": "registry",
            "id": "android.support.v4"
        }
    },
    "de.appplant.cordova.common.registerusernotificationsettings": {
        "source": {
            "type": "registry",
            "id": "de.appplant.cordova.common.registerusernotificationsettings"
        }
    },
    "de.appplant.cordova.plugin.background-mode": {
        "source": {
            "type": "git",
            "url": "https://github.com/katzer/cordova-plugin-background-mode.git",
            "subdir": "."
        }
    },
    "com.teamnemitoff.phonedialer": {
        "source": {
            "type": "git",
            "url": "https://github.com/anemitoff/PhoneGap-PhoneDialer.git",
            "subdir": "."
        },
        "is_top_level": true,
        "variables": {}
    },
    "org.apache.cordova.dialogs": {
        "source": {
            "type": "registry",
            "id": "org.apache.cordova.dialogs"
        },
        "is_top_level": true,
        "variables": {}
    },
    "com.jsmobile.plugins.sms": {
        "source": {
            "type": "registry",
            "id": "com.jsmobile.plugins.sms"
        },
        "is_top_level": true,
        "variables": {}
    }
}